{
    "id": 406,
    "description": "Given a string s and a dictionary of strings wordDict, return true if s can be segmented into a space-separated sequence of one or more dictionary words.\n\nNote that the same word in the dictionary may be reused multiple times in the segmentation.\n\n### Example 1 \n### Input\n```CPP\nn = 2\nWordDict = [\"leet\",\"code\"]\nword = \"leetcode\"\n``` \n\n### Output\n```CPP\n1\n``` \n\n\n### Constraints\n\n* 1 <= WordDict.size() <= 100\n* 1 <=WordDict[i].size() <=1000\n*  1 <=word.size() <=1000",
    "title": "Word Break",
    "default_testcase": {
        "id": 2537,
        "input": "applepenapple\n2\napple pen",
        "expected_output": "true\n",
        "code_problem_id": 406,
        "created_at": "2023-11-21T05:27:43.041Z",
        "updated_at": "2023-11-21T05:27:43.041Z"
    },
    "problem_type": "practice",
    "code_skeletons": [
        {
            "id": 989,
            "code_problem_id": 406,
            "language": {
                "id": 11,
                "name": "C++ (GCC 9.2.0)",
                "judge0_language_id": 54
            },
            "skeleton_define_class": null,
            "skeleton_class_end": null,
            "skeleton_solution_class": "class Solution{\n    public:\n    // A : given string to search\n    // B : vector of available strings\n    \n    int wordBreak(string A, vector<string> &B) {\n        //code here\n    }\n};\n"
        },
        {
            "id": 990,
            "code_problem_id": 406,
            "language": {
                "id": 25,
                "name": "Java (OpenJDK 13.0.1)",
                "judge0_language_id": 62
            },
            "skeleton_define_class": null,
            "skeleton_class_end": null,
            "skeleton_solution_class": "class Solution\n{\n    public static int wordBreak(String A, ArrayList<String> B )\n    {\n        //code here\n    }\n}"
        },
        {
            "id": 991,
            "code_problem_id": 406,
            "language": {
                "id": 39,
                "name": "Python (3.8.1)",
                "judge0_language_id": 71
            },
            "skeleton_define_class": null,
            "skeleton_class_end": null,
            "skeleton_solution_class": "class Solution:\n    def wordBreak(self, A, B):"
        },
        {
            "id": 1048,
            "code_problem_id": 406,
            "language": {
                "id": 26,
                "name": "JavaScript (Node.js 12.14.0)",
                "judge0_language_id": 63
            },
            "skeleton_define_class": null,
            "skeleton_class_end": null,
            "skeleton_solution_class": "class Solution {\n    wordBreak(A, B) {\n        // Your implementation goes here\n    }\n}"
        }
    ]
}